hardware/conv2D.v
`timescale 1ns / 1ps

module conv2D(
    // clock and reset ports - since both AXI buses are on the same clock in the block diagram, we only need one of each
    input wire  M_AXIS_ACLK,
    input wire  M_AXIS_ARESETN,
    input wire  S_AXIS_ACLK,
	input wire  S_AXIS_ARESETN,
    
    //master AXI interface - sends data back to DRAM
    output wire  M_AXIS_TVALID, // Master Stream Ports. TVALID indicates that the master is driving a valid transfer, A transfer takes place when both TVALID and TREADY are asserted. 
    output wire [15:0] M_AXIS_TDATA, // TDATA is the primary payload that is used to provide the data that is passing across the interface from the master.
    output wire [1:0] M_AXIS_TKEEP, // 
    output wire  M_AXIS_TLAST, // TLAST indicates the boundary of a packet.
    input wire  M_AXIS_TREADY, // TREADY indicates that the slave can accept a transfer in the current cycle.
    
    //slave AXI interface - recieves data from DRAM
    output wire  S_AXIS_TREADY, // Ready to accept data in
    input wire [15:0] S_AXIS_TDATA, // Data in
    input wire [1:0] S_AXIS_TKEEP, // almost always high - indicates that data bytes are not null
    input wire  S_AXIS_TLAST, // Indicates boundary of last packet
    input wire  S_AXIS_TVALID // Data is in valid
    );
    
    // // // outputs
    // wire [15:0] products1,products2,products3,products4,products5,products6,products7,products8,products9;
    // assign products1 = products[0][0];
    // assign products2 = products[0][1];
    // assign products3 = products[0][2];
    // assign products4 = products[1][0];
    // assign products5 = products[1][1];
    // assign products6 = products[1][2];
    // assign products7 = products[2][0];
    // assign products8 = products[2][1];
    // assign products9 = products[2][2];

    // wire [15:0] filter1,filter2,filter3,filter4,filter5,filter6,filter7,filter8,filter9;
    // assign filter1 = filter[0][0];
    // assign filter2 = filter[0][1];
    // assign filter3 = filter[0][2];
    // assign filter4 = filter[1][0];
    // assign filter5 = filter[1][1];
    // assign filter6 = filter[1][2];
    // assign filter7 = filter[2][0];
    // assign filter8 = filter[2][1];
    // assign filter9 = filter[2][2];

    // wire [15:0] data1,data2,data3,data4,data5,data6,data7,data8,data9;
    // assign data1 = data[0][0];
    // assign data2 = data[0][1];
    // assign data3 = data[0][2];
    // assign data4 = data[1][0];
    // assign data5 = data[1][1];
    // assign data6 = data[1][2];
    // assign data7 = data[2][0];
    // assign data8 = data[2][1];
    // assign data9 = data[2][2];


    //==========================================================================================================
    //Combinatorial state interpretation rules
    reg [2:0] state;
    //000: 0: IDLE
    //001: 1: FILTER_RX (recieving filter data)
    //010: 2: PROC1 (begin recieving actual data, but not yet transmitting data)
    //011: 3: PROC2 (reciving and transmitting data)
    //100: 4: PROC3 (done recieving data, but still need to transmit data)
    
    //extra flags for indicating when things should happen / are happening
    wire TX, RX, RX_data, RX_last, systolic_advance, new_filt_data, arr_rst, new_data, zero_padding, TX_last;
    assign RX = S_AXIS_TREADY && S_AXIS_TVALID;
    assign TX = M_AXIS_TREADY && M_AXIS_TVALID && (row_count == 2); //internal flag: we transmitted a word to output stream
    assign RX_data = RX && S_AXIS_TKEEP == 3; //internal flag: we recieved a word from input stream
    assign RX_last = RX && S_AXIS_TLAST;
    assign systolic_advance = zero_padding || arr_rst || new_data; //indicates when the systolic array should step forward
    assign new_filt_data = (state == 0 || state == 1) && RX_data;
    //assign arr_rst = (state == 0 && ~RX);
    assign arr_rst = (state == 0 && ~RX) || S_AXIS_ARESETN;
    assign new_data = (state == 2 || state == 3) && RX_data;
    //TODO: change w/o row_count and add TX
    assign zero_padding = state == 4 && (row_count != 2); //pad a zero into array if we are in last state and are transmitting data as well
    assign TX_last = TX_count == data_count / 3  - 2; // this is for full convolution
    
    //AXI interface control 
    assign M_AXIS_TVALID = state == 4 || (state == 3 && S_AXIS_TVALID); //
    assign M_AXIS_TKEEP = 3; //always on, since this design is guarenteed to transmit last DATA and TLAST on the same clock edge
    assign M_AXIS_TLAST = (state == 4) && TX_last;//if there is only one more transmission needed, assert last on that transmission
    assign S_AXIS_TREADY = M_AXIS_TREADY;//we are generally always ready, unless the next stage is not
    
    
    //===========================================================================================================
    //filter loading: shift register that fills up in first state, and is stationary during systolic calculation
    reg [15:0] filter[0:2][0:2];
    reg [8:0] filter_size;
    
    always @(posedge S_AXIS_ACLK) begin 
        if (new_filt_data) begin
            filter[0][0] <= S_AXIS_TDATA; //shift register input
            filter_size <= filter_size + 1;
        end
        else if (arr_rst) begin
            filter[0][0] <= 0; //load zeros in order to reset
            filter_size <= 0;
        end
    end
    
    genvar row, col;
    generate
    for (row=0; row<3; row=row+1) begin
        for (col=0; col<3; col=col+1) begin
            always @(posedge S_AXIS_ACLK) begin
                if (new_filt_data || arr_rst) begin
                    // filter[0][0] taken care in previous block
                    if(row != 0 && col == 0) filter[row][0] <= filter[row-1][2];
                    if(col != 0) filter[row][col] <= filter[row][col-1];
                end
            end
        end
    end

    endgenerate
    
    //============================================================================================================
    //data shift register: looks exactly like filter register, but continually passes data through while running computation
    //also count data TX here
    reg [15:0] data[0:2][0:2];
    reg [31:0] data_count;
    reg [31:0] row_count;
    reg [31:0] TX_count;
    
    always @(posedge S_AXIS_ACLK) begin
        if (new_data) begin 
            data[row_count][2] <= S_AXIS_TDATA; //shift register input
            data_count <= data_count+1;
            //Reset & count rows
            if (row_count != 2) row_count <= row_count + 1;
            if (row_count == 2) row_count <= 0;
        end
        if (zero_padding) begin
            data[row_count][2] <= 0; //zero padding at end
            if (row_count != 2) row_count <= row_count + 1;
            if (row_count == 2) row_count <= 0;
        end
        if (arr_rst) begin
            data_count <= 0;
            row_count <= 0;
            data[0][2] <= 0;
            data[1][2] <= 0;
            data[2][2] <= 0;
        end
        if (TX) TX_count <= TX_count + 1;
        if (arr_rst) TX_count <= 0;
    end

    generate
    for (col=2; col>0; col=col-1) begin
        always @(posedge S_AXIS_ACLK) begin
            if (systolic_advance) begin
                // data[0][0] taken care in previous block
                if(row_count == 0 || arr_rst) data[0][col-1] <= data[0][col];
                if(row_count == 1 || arr_rst) data[1][col-1] <= data[1][col];
                if(row_count == 2 || arr_rst) data[2][col-1] <= data[2][col];
            end 
        end
    end
    endgenerate
    
    //============================================================================================================
    //systolic array math: 256 multipliers, and 255 adders in a binary tree
    reg [15:0] products[0:2][0:2];
    reg [15:0] L0sums[0:2];
    
    assign M_AXIS_TDATA = L0sums[0] + L0sums[1] + L0sums[2];
    
    generate
        // perform product
        for (col=0; col<3; col=col+1) begin 
            always @(posedge S_AXIS_ACLK) begin
                if (systolic_advance) begin
                    products[0][col] <= data[0][col]*filter[0][col]; 
                    products[1][col] <= data[1][col]*filter[1][col]; 
                    products[2][col] <= data[2][col]*filter[2][col]; 
                end
            end
        end
        for(row=0; row<3; row=row+1) begin
            always @(posedge S_AXIS_ACLK) begin
                if (systolic_advance) begin
                    L0sums[row] <= products[row][0] + products[row][1] + products[row][2];
                end
            end
        end
        
    endgenerate
    
    //=================================================================================================================================
    //rules for changing system state
    
    always @(posedge S_AXIS_ACLK) begin
        if (arr_rst) begin
            state <= 0;
        end
        else begin
        if (state == 0 && RX_data) state <= 1; //start loading to filter array after being in idle state
        if (state == 1 && RX_last) state <= 2; //when done loading to filter array, move to processing state
        if (state == 2 && data_count == 10 && RX_data) state <= 3; //once first data conv has propegated through arithmetic, move to send&receive state
        if (state == 3 && RX_last) state <= 4; //once all data has been received, move to send-only state
        if (state == 4 && TX && TX_last) state <= 0; //once all results have been sent, return to idle state
        end
    end
    
endmodule

hardware/tb_project.sv
// Code your testbench here
// or browse Examples
module tb_conv2d;
  reg M_AXIS_ACLK;
  reg M_AXIS_ARESETN;
  reg S_AXIS_ACLK;
  reg S_AXIS_ARESETN;
  
  reg M_AXIS_TREADY;
  reg [15:0] S_AXIS_TDATA;
  reg [1:0] S_AXIS_TKEEP;
  reg  S_AXIS_TLAST;
  reg  S_AXIS_TVALID;
  
  wire M_AXIS_TVALID;
  wire [15:0] M_AXIS_TDATA;
  wire [1:0] M_AXIS_TKEEP;
  wire M_AXIS_TLAST;
  wire S_AXIS_TREADY;
  
  conv2D dut(.M_AXIS_ACLK(M_AXIS_ACLK), 
                .M_AXIS_ARESETN(M_AXIS_ARESETN),
                .S_AXIS_ACLK(M_AXIS_ACLK),
                .S_AXIS_ARESETN(S_AXIS_ARESETN),
                .M_AXIS_TVALID(M_AXIS_TVALID),
                .M_AXIS_TDATA(M_AXIS_TDATA),
                .M_AXIS_TKEEP(M_AXIS_TKEEP),
                .M_AXIS_TLAST(M_AXIS_TLAST),
                .M_AXIS_TREADY(M_AXIS_TREADY),
                .S_AXIS_TREADY(S_AXIS_TREADY),
                .S_AXIS_TDATA(S_AXIS_TDATA),
                .S_AXIS_TKEEP(S_AXIS_TKEEP),
                .S_AXIS_TLAST(S_AXIS_TLAST),
                .S_AXIS_TVALID(S_AXIS_TVALID)
                );
  
  always
    begin
      #5 M_AXIS_ACLK = ~M_AXIS_ACLK;
    end
  
  initial
    begin
      $dumpfile("dump.vcd");
      $dumpvars();
      
      M_AXIS_ACLK = 0;
      S_AXIS_ACLK = 0;
      
      // reset
      M_AXIS_ARESETN = 0;
      S_AXIS_ARESETN = 0;
      S_AXIS_TLAST = 0;
      # 10
      
      M_AXIS_ARESETN = 1;
      S_AXIS_ARESETN = 1; 
      # 100

      // weights
      M_AXIS_ARESETN = 0;
      S_AXIS_ARESETN = 0; 
      M_AXIS_TREADY = 1;
      S_AXIS_TKEEP = 3;
      S_AXIS_TVALID = 1;
 
      S_AXIS_TDATA = 1;
      # 10
      S_AXIS_TDATA = 2;
      # 10
      S_AXIS_TDATA = 3;
      # 10
      S_AXIS_TDATA = 4;
      # 10
      S_AXIS_TDATA = 5;
      # 10
      S_AXIS_TDATA = 6;
      # 10
      S_AXIS_TDATA = 7;
      # 10
      S_AXIS_TDATA = 8;
      # 10
      S_AXIS_TDATA = 9;
      S_AXIS_TLAST = 1;
      # 10

      S_AXIS_TVALID = 0;
      # 10

      // inputs
      
      # 10
      S_AXIS_TLAST = 0;
      S_AXIS_TVALID = 1;
      S_AXIS_TDATA = 0;
      # 10
      S_AXIS_TDATA = 0;
      # 10
      S_AXIS_TDATA = 0;
      # 10
      S_AXIS_TDATA = 0;
      # 10
      S_AXIS_TDATA = 1;
      # 10
      S_AXIS_TDATA = 6;
      # 10
      S_AXIS_TDATA = 0;
      # 10
      S_AXIS_TDATA = 2;
      # 10
      S_AXIS_TDATA = 7;
      # 10
      S_AXIS_TDATA = 0;
      # 10
      S_AXIS_TDATA = 3;
      # 10
      S_AXIS_TDATA = 8;
      # 10
      S_AXIS_TDATA = 0;
      # 10
      S_AXIS_TDATA = 4;
      # 10
      S_AXIS_TDATA = 9;
      # 10
      S_AXIS_TDATA = 0;
      # 10
      S_AXIS_TDATA = 5;
      # 10
      S_AXIS_TDATA = 10;
      # 10
      S_AXIS_TDATA = 0;
      # 10
      S_AXIS_TDATA = 0;
      # 10
      S_AXIS_TDATA = 0;
      S_AXIS_TLAST = 1;
      # 10
      S_AXIS_TVALID = 0;

      #800
      
      
      $display("FINSIHED PREDICTION");
      $finish;
      
    end
  
endmodule

hardware/testing/test.sim/sim_1/behav/xsim/dump.vcd
$date
   Sun Dec  5 13:47:04 2021
$end
$version
  2020.2
$end
$timescale
  1ps
$end
$scope module tb_conv2d $end
$var reg 1 ! M_AXIS_ACLK $end
$var reg 1 " M_AXIS_ARESETN $end
$var reg 1 # S_AXIS_ACLK $end
$var reg 1 $ S_AXIS_ARESETN $end
$var reg 1 % M_AXIS_TREADY $end
$var reg 16 & S_AXIS_TDATA [15:0] $end
$var reg 2 ' S_AXIS_TKEEP [1:0] $end
$var reg 1 ( S_AXIS_TLAST $end
$var reg 1 ) S_AXIS_TVALID $end
$var wire 1 * M_AXIS_TVALID $end
$var wire 16 + M_AXIS_TDATA [15:0] $end
$var wire 2 , M_AXIS_TKEEP [1:0] $end
$var wire 1 - M_AXIS_TLAST $end
$var wire 1 . S_AXIS_TREADY $end
$scope module dut $end
$var wire 1 / M_AXIS_ACLK $end
$var wire 1 0 M_AXIS_ARESETN $end
$var wire 1 1 S_AXIS_ACLK $end
$var wire 1 2 S_AXIS_ARESETN $end
$var wire 1 * M_AXIS_TVALID $end
$var wire 16 + M_AXIS_TDATA [15:0] $end
$var wire 2 , M_AXIS_TKEEP [1:0] $end
$var wire 1 - M_AXIS_TLAST $end
$var wire 1 3 M_AXIS_TREADY $end
$var wire 1 . S_AXIS_TREADY $end
$var wire 16 4 S_AXIS_TDATA [15:0] $end
$var wire 2 5 S_AXIS_TKEEP [1:0] $end
$var wire 1 6 S_AXIS_TLAST $end
$var wire 1 7 S_AXIS_TVALID $end
$var reg 3 8 state [2:0] $end
$var wire 1 9 TX $end
$var wire 1 : RX $end
$var wire 1 ; RX_data $end
$var wire 1 < RX_last $end
$var wire 1 = systolic_advance $end
$var wire 1 > new_filt_data $end
$var wire 1 ? arr_rst $end
$var wire 1 @ new_data $end
$var wire 1 A zero_padding $end
$var wire 1 B TX_last $end
$var reg 9 C filter_size [8:0] $end
$var reg 32 D data_count [31:0] $end
$var reg 32 E row_count [31:0] $end
$var reg 32 F TX_count [31:0] $end
$upscope $end
$upscope $end
$enddefinitions $end
#0
$dumpvars
0!
0"
0#
0$
x%
bx &
bx '
0(
x)
x*
bx +
b11 ,
x-
x.
0/
00
01
02
x3
bx 4
bx 5
06
x7
bx 8
x9
x:
x;
0<
x=
x>
x?
x@
xA
xB
bx C
bx D
bx E
bx F
$end
#5000
1!
1/
11
#10000
0!
1"
1$
0/
10
01
12
1=
1?
#15000
1!
0*
0-
1/
11
b0 8
09
1=
x>
1?
0@
0A
0B
b0 C
b0 D
b0 E
b0 F
#20000
0!
0/
01
#25000
1!
1/
11
b0 8
b0 C
b0 D
b0 E
b0 F
#30000
0!
0/
01
#35000
1!
1/
11
b0 8
b0 C
b0 D
b0 E
b0 F
#40000
0!
0/
01
#45000
1!
1/
11
b0 8
b0 C
b0 D
b0 E
b0 F
#50000
0!
0/
01
#55000
1!
bx +
1/
11
b0 8
b0 C
b0 D
b0 E
b0 F
#60000
0!
0/
01
#65000
1!
1/
11
b0 8
b0 C
b0 D
b0 E
b0 F
#70000
0!
0/
01
#75000
1!
1/
11
b0 8
b0 C
b0 D
b0 E
b0 F
#80000
0!
0/
01
#85000
1!
bx +
1/
11
b0 8
b0 C
b0 D
b0 E
b0 F
#90000
0!
0/
01
#95000
1!
1/
11
b0 8
b0 C
b0 D
b0 E
b0 F
#100000
0!
0/
01
#105000
1!
1/
11
b0 8
b0 C
b0 D
b0 E
b0 F
#110000
0!
0"
0$
1%
b1 &
b11 '
1)
0*
1.
0/
00
01
02
13
b1 4
b11 5
17
09
1:
1;
0<
0=
1>
0?
0@
#115000
1!
0*
0-
1/
11
b1 8
1>
0?
0@
0A
b1 C
#120000
0!
b10 &
0/
01
b10 4
#125000
1!
1/
11
b10 C
#130000
0!
b11 &
0/
01
b11 4
#135000
1!
1/
11
b11 C
#140000
0!
b100 &
0/
01
b100 4
#145000
1!
1/
11
b100 C
#150000
0!
b101 &
0/
01
b101 4
#155000
1!
1/
11
b101 C
#160000
0!
b110 &
0/
01
b110 4
#165000
1!
1/
11
b110 C
#170000
0!
b111 &
0/
01
b111 4
#175000
1!
1/
11
b111 C
#180000
0!
b1000 &
0/
01
b1000 4
#185000
1!
1/
11
b1000 C
#190000
0!
b1001 &
1(
0/
01
b1001 4
16
1<
#195000
1!
0*
0-
1/
11
b10 8
1=
0>
0?
1@
0A
b1001 C
#200000
0!
0)
0*
0/
01
07
0:
0;
0<
0=
0>
0?
0@
#205000
1!
1/
11
#210000
0!
0/
01
#215000
1!
1/
11
#220000
0!
b0 &
0(
1)
0*
0/
01
b0 4
06
17
1:
1;
0<
1=
0>
0?
1@
#225000
1!
b0 +
1/
11
09
0A
0B
b1 D
b1 E
#230000
0!
b0 &
0/
01
#235000
1!
1/
11
09
0A
0B
b10 D
b10 E
#240000
0!
b0 &
0/
01
#245000
1!
1/
11
09
0A
0B
b11 D
b0 E
#250000
0!
b0 &
0/
01
#255000
1!
1/
11
09
0A
0B
b100 D
b1 E
#260000
0!
b1 &
0/
01
b1 4
#265000
1!
1/
11
09
0A
0B
b101 D
b10 E
#270000
0!
b110 &
0/
01
b110 4
#275000
1!
0-
1/
11
09
0A
1B
b110 D
b0 E
#280000
0!
b0 &
0/
01
b0 4
#285000
1!
b100 +
1/
11
09
0A
1B
b111 D
b1 E
#290000
0!
b10 &
0/
01
b10 4
#295000
1!
b1010 +
1/
11
09
0A
1B
b1000 D
b10 E
#300000
0!
b111 &
0/
01
b111 4
#305000
1!
0-
1/
11
09
0A
0B
b1001 D
b0 E
#310000
0!
b0 &
0/
01
b0 4
#315000
1!
b10011 +
1/
11
09
0A
0B
b1010 D
b1 E
#320000
0!
b11 &
0/
01
b11 4
#325000
1!
1*
b100000 +
0-
1/
11
b11 8
19
0>
0?
1@
0A
0B
b1011 D
b10 E
#330000
0!
b1000 &
0/
01
b1000 4
#335000
1!
1/
11
09
0A
0B
b1100 D
b0 E
b1 F
#340000
0!
b0 &
0/
01
b0 4
#345000
1!
b101111 +
1/
11
09
0A
0B
b1101 D
b1 E
#350000
0!
b100 &
0/
01
b100 4
#355000
1!
b1000100 +
1/
11
19
0A
0B
b1110 D
b10 E
#360000
0!
b1001 &
0/
01
b1001 4
#365000
1!
1/
11
09
0A
0B
b1111 D
b0 E
b10 F
#370000
0!
b0 &
0/
01
b0 4
#375000
1!
b1010011 +
1/
11
09
0A
0B
b10000 D
b1 E
#380000
0!
b101 &
0/
01
b101 4
#385000
1!
b1011001 +
1/
11
19
0A
0B
b10001 D
b10 E
#390000
0!
b1010 &
0/
01
b1010 4
#395000
1!
1/
11
09
0A
0B
b10010 D
b0 E
b11 F
#400000
0!
b0 &
0/
01
b0 4
#405000
1!
b1101000 +
1/
11
09
0A
0B
b10011 D
b1 E
#410000
0!
b0 &
0/
01
#415000
1!
b1101110 +
1/
11
19
0A
0B
b10100 D
b10 E
#420000
0!
b0 &
1(
0/
01
16
1<
#425000
1!
1*
0-
1/
11
b100 8
09
1=
0>
0?
0@
1A
0B
b10101 D
b0 E
b100 F
#430000
0!
0)
1*
0/
01
07
0:
0;
0<
0>
0?
0@
#435000
1!
b1100101 +
1/
11
09
1A
b1 E
#440000
0!
0/
01
#445000
1!
b1100000 +
1/
11
19
0=
0A
b10 E
#450000
0!
0/
01
#455000
1!
1-
1/
11
1B
b101 F
#460000
0!
0/
01
#465000
1!
0*
0-
1/
11
b0 8
09
1=
0>
1?
0@
0A
0B
b110 F
#470000
0!
0/
01
#475000
1!
1/
11
b0 8
09
0A
0B
b0 C
b0 D
b0 E
b0 F
#480000
0!
0/
01
#485000
1!
b1001101 +
1/
11
b0 8
b0 C
b0 D
b0 E
b0 F
#490000
0!
0/
01
#495000
1!
b101000 +
1/
11
b0 8
b0 C
b0 D
b0 E
b0 F
#500000
0!
0/
01
#505000
1!
b0 +
1/
11
b0 8
b0 C
b0 D
b0 E
b0 F
#510000
0!
0/
01
#515000
1!
1/
11
b0 8
b0 C
b0 D
b0 E
b0 F
#520000
0!
0/
01
#525000
1!
1/
11
b0 8
b0 C
b0 D
b0 E
b0 F
#530000
0!
0/
01
#535000
1!
1/
11
b0 8
b0 C
b0 D
b0 E
b0 F
#540000
0!
0/
01
#545000
1!
1/
11
b0 8
b0 C
b0 D
b0 E
b0 F
#550000
0!
0/
01
#555000
1!
1/
11
b0 8
b0 C
b0 D
b0 E
b0 F
#560000
0!
0/
01
#565000
1!
1/
11
b0 8
b0 C
b0 D
b0 E
b0 F
#570000
0!
0/
01
#575000
1!
1/
11
b0 8
b0 C
b0 D
b0 E
b0 F
#580000
0!
0/
01
#585000
1!
1/
11
b0 8
b0 C
b0 D
b0 E
b0 F
#590000
0!
0/
01
#595000
1!
1/
11
b0 8
b0 C
b0 D
b0 E
b0 F
#600000
0!
0/
01
#605000
1!
1/
11
b0 8
b0 C
b0 D
b0 E
b0 F
#610000
0!
0/
01
#615000
1!
1/
11
b0 8
b0 C
b0 D
b0 E
b0 F
#620000
0!
0/
01
#625000
1!
1/
11
b0 8
b0 C
b0 D
b0 E
b0 F
#630000
0!
0/
01
#635000
1!
1/
11
b0 8
b0 C
b0 D
b0 E
b0 F
#640000
0!
0/
01
#645000
1!
1/
11
b0 8
b0 C
b0 D
b0 E
b0 F
#650000
0!
0/
01
#655000
1!
1/
11
b0 8
b0 C
b0 D
b0 E
b0 F
#660000
0!
0/
01
#665000
1!
1/
11
b0 8
b0 C
b0 D
b0 E
b0 F
#670000
0!
0/
01
#675000
1!
1/
11
b0 8
b0 C
b0 D
b0 E
b0 F
#680000
0!
0/
01
#685000
1!
1/
11
b0 8
b0 C
b0 D
b0 E
b0 F
#690000
0!
0/
01
#695000
1!
1/
11
b0 8
b0 C
b0 D
b0 E
b0 F
#700000
0!
0/
01
#705000
1!
1/
11
b0 8
b0 C
b0 D
b0 E
b0 F
#710000
0!
0/
01
#715000
1!
1/
11
b0 8
b0 C
b0 D
b0 E
b0 F
#720000
0!
0/
01
#725000
1!
1/
11
b0 8
b0 C
b0 D
b0 E
b0 F
#730000
0!
0/
01
#735000
1!
1/
11
b0 8
b0 C
b0 D
b0 E
b0 F
#740000
0!
0/
01
#745000
1!
1/
11
b0 8
b0 C
b0 D
b0 E
b0 F
#750000
0!
0/
01
#755000
1!
1/
11
b0 8
b0 C
b0 D
b0 E
b0 F
#760000
0!
0/
01
#765000
1!
1/
11
b0 8
b0 C
b0 D
b0 E
b0 F
#770000
0!
0/
01
#775000
1!
1/
11
b0 8
b0 C
b0 D
b0 E
b0 F
#780000
0!
0/
01
#785000
1!
1/
11
b0 8
b0 C
b0 D
b0 E
b0 F
#790000
0!
0/
01
#795000
1!
1/
11
b0 8
b0 C
b0 D
b0 E
b0 F
#800000
0!
0/
01
#805000
1!
1/
11
b0 8
b0 C
b0 D
b0 E
b0 F
#810000
0!
0/
01
#815000
1!
1/
11
b0 8
b0 C
b0 D
b0 E
b0 F
#820000
0!
0/
01
#825000
1!
1/
11
b0 8
b0 C
b0 D
b0 E
b0 F
#830000
0!
0/
01
#835000
1!
1/
11
b0 8
b0 C
b0 D
b0 E
b0 F
#840000
0!
0/
01
#845000
1!
1/
11
b0 8
b0 C
b0 D
b0 E
b0 F
#850000
0!
0/
01
#855000
1!
1/
11
b0 8
b0 C
b0 D
b0 E
b0 F
#860000
0!
0/
01
#865000
1!
1/
11
b0 8
b0 C
b0 D
b0 E
b0 F
#870000
0!
0/
01
#875000
1!
1/
11
b0 8
b0 C
b0 D
b0 E
b0 F
#880000
0!
0/
01
#885000
1!
1/
11
b0 8
b0 C
b0 D
b0 E
b0 F
#890000
0!
0/
01
#895000
1!
1/
11
b0 8
b0 C
b0 D
b0 E
b0 F
#900000
0!
0/
01
#905000
1!
1/
11
b0 8
b0 C
b0 D
b0 E
b0 F
#910000
0!
0/
01
#915000
1!
1/
11
b0 8
b0 C
b0 D
b0 E
b0 F
#920000
0!
0/
01
#925000
1!
1/
11
b0 8
b0 C
b0 D
b0 E
b0 F
#930000
0!
0/
01
#935000
1!
1/
11
b0 8
b0 C
b0 D
b0 E
b0 F
#940000
0!
0/
01
#945000
1!
1/
11
b0 8
b0 C
b0 D
b0 E
b0 F
#950000
0!
0/
01
#955000
1!
1/
11
b0 8
b0 C
b0 D
b0 E
b0 F
#960000
0!
0/
01
#965000
1!
1/
11
b0 8
b0 C
b0 D
b0 E
b0 F
#970000
0!
0/
01
#975000
1!
1/
11
b0 8
b0 C
b0 D
b0 E
b0 F
#980000
0!
0/
01
#985000
1!
1/
11
b0 8
b0 C
b0 D
b0 E
b0 F
#990000
0!
0/
01
#995000
1!
1/
11
b0 8
b0 C
b0 D
b0 E
b0 F
